mypackage/__init__.py
mypackage/student_records.py
mypackage_theacodes-0.1.dist-info/METADATA
mypackage_theacodes-0.1.dist-info/WHEEL
mypackage_theacodes-0.1.dist-info/top_level.txt
mypackage_theacodes-0.1.dist-info/RECORD
