Metadata-Version: 2.1
Name: mypackage-theacodes
Version: 0.1
Summary: Progetto di Produzione del Software
Home-page: https://gitlab.com/MarcecaManu/test_runner
Author: Simone
Author-email: s.madaghiele@campus.unimib.it
Requires-Dist: requirements.txt
